airflow/providers/anomalo/__init__.py
airflow/providers/anomalo/example_dags/__init__.py
airflow/providers/anomalo/example_dags/example_anomalo.py
airflow/providers/anomalo/hooks/__init__.py
airflow/providers/anomalo/hooks/anomalo.py
airflow/providers/anomalo/operators/__init__.py
airflow/providers/anomalo/operators/anomalo.py
airflow/providers/anomalo/sensors/__init__.py
airflow/providers/anomalo/sensors/anomalo.py
apache_airflow_providers_anomalo-0.2.2.dist-info/entry_points.txt
apache_airflow_providers_anomalo-0.2.2.dist-info/LICENSE
apache_airflow_providers_anomalo-0.2.2.dist-info/WHEEL
apache_airflow_providers_anomalo-0.2.2.dist-info/METADATA
apache_airflow_providers_anomalo-0.2.2.dist-info/RECORD
