Metadata-Version: 2.1
Name: apache-airflow-providers-anomalo
Version: 0.2.2
Summary: An Apache Airflow provider for Anomalo
Home-page: https://github.com/anomalo-hq/anomalo-airflow-provider
License: Apache-2.0
Author: Anomalo
Author-email: opensource@anomalo.com
Requires-Python: >=3.8,<3.12
Classifier: Development Status :: 5 - Production/Stable
Classifier: Framework :: Apache Airflow
Classifier: Framework :: Apache Airflow :: Provider
Classifier: Intended Audience :: Developers
Classifier: License :: OSI Approved :: Apache Software License
Classifier: Operating System :: OS Independent
Classifier: Programming Language :: Python :: 3
Classifier: Programming Language :: Python :: 3.8
Classifier: Programming Language :: Python :: 3.9
Classifier: Programming Language :: Python :: 3.10
Classifier: Programming Language :: Python :: 3.11
Requires-Dist: anomalo (>=0.17.0,<0.18.0)
Requires-Dist: importlib-resources (>=6.1.1,<7.0.0)
Project-URL: Repository, https://github.com/anomalo-hq/anomalo-airflow-provider
